alliteration/__init__.py
alliteration-0.0.2.dist-info/LICENSE.md
alliteration-0.0.2.dist-info/METADATA
alliteration-0.0.2.dist-info/WHEEL
alliteration-0.0.2.dist-info/top_level.txt
alliteration-0.0.2.dist-info/RECORD
