Metadata-Version: 2.1
Name: alliteration
Version: 0.0.2
Summary: AI to boost your alliteration skills!
Home-page: https://github.com/AgarwalPragy/alliteration
Author: Pragy Agarwal
Author-email: agar.pragy@gmail.com
License: BSD
Download-URL: https://github.com/AgarwalPragy/alliteration/tarball/0.0.2
Platform: UNKNOWN
Classifier: Development Status :: 3 - Alpha
Classifier: Intended Audience :: Developers
Classifier: Programming Language :: Python :: 3
Requires-Dist: sphinx
Requires-Dist: sphinx-rtd-theme
Requires-Dist: nose
Requires-Dist: coverage
Requires-Dist: pypi-publisher
